pytest_forger/__init__.py
pytest_forger/__version__.py
pytest_forger/cli.py
pytest_forger-0.1.1.dist-info/licenses/LICENSE
pytest_forger-0.1.1.dist-info/METADATA
pytest_forger-0.1.1.dist-info/WHEEL
pytest_forger-0.1.1.dist-info/entry_points.txt
pytest_forger-0.1.1.dist-info/top_level.txt
pytest_forger-0.1.1.dist-info/RECORD
