Metadata-Version: 2.4
Name: pytest-forger
Version: 0.1.1
Summary: Automatic test scaffolding and mock generation for Python
Author-email: Daryll Lorenzo Alfonso <daryllla77@gmail.com>
License-Expression: MIT
Project-URL: Homepage, https://github.com/DaryllLorenzo/pytest-forger
Project-URL: Repository, https://github.com/DaryllLorenzo/pytest-forger
Project-URL: Issues, https://github.com/DaryllLorenzo/pytest-forger/issues
Classifier: Programming Language :: Python :: 3
Classifier: Operating System :: OS Independent
Classifier: Intended Audience :: Developers
Classifier: Environment :: Console
Classifier: Topic :: Software Development :: Testing
Requires-Python: >=3.9
License-File: LICENSE
Requires-Dist: typer>=0.9.0
Requires-Dist: pytest>=7.4.0
Provides-Extra: dev
Requires-Dist: build; extra == "dev"
Requires-Dist: twine; extra == "dev"
Dynamic: license-file
